netbox_api_token_generator/__init__.py
netbox_api_token_generator/api/urls.py
netbox_api_token_generator/api/views.py
netbox_api_token_generator-0.1.dist-info/LICENSE
netbox_api_token_generator-0.1.dist-info/METADATA
netbox_api_token_generator-0.1.dist-info/WHEEL
netbox_api_token_generator-0.1.dist-info/top_level.txt
netbox_api_token_generator-0.1.dist-info/RECORD
