Metadata-Version: 2.1
Name: netbox-api-token-generator
Version: 0.1
Summary: NetBox plugin to generate API token for a user
Home-page: https://github.com/agrawald/netbox_api_token_generator.git
Author: Dheeraj Agrawal
Author-email: agrawal.dheeraj.7@gmail.com
License: Apache 2.0
Platform: UNKNOWN
License-File: LICENSE
